tock_genai_core/__init__.py
tock_genai_core/models/__init__.py
tock_genai_core/models/contextual_compressor/__init__.py
tock_genai_core/models/contextual_compressor/bloomz/__init__.py
tock_genai_core/models/contextual_compressor/bloomz/bloomz_compressor_setting.py
tock_genai_core/models/contextual_compressor/provider.py
tock_genai_core/models/contextual_compressor/setting.py
tock_genai_core/models/contextual_compressor/types.py
tock_genai_core/models/database/__init__.py
tock_genai_core/models/database/metadata.py
tock_genai_core/models/database/opensearch/__init__.py
tock_genai_core/models/database/opensearch/opensearch_db_setting.py
tock_genai_core/models/database/pgvector/__init__.py
tock_genai_core/models/database/pgvector/pgvector_db_setting.py
tock_genai_core/models/database/provider.py
tock_genai_core/models/database/setting.py
tock_genai_core/models/database/types.py
tock_genai_core/models/embedding/__init__.py
tock_genai_core/models/embedding/azure_openai/__init__.py
tock_genai_core/models/embedding/azure_openai/azure_openai_em_setting.py
tock_genai_core/models/embedding/bloomz/__init__.py
tock_genai_core/models/embedding/bloomz/bloomz_em_setting.py
tock_genai_core/models/embedding/provider.py
tock_genai_core/models/embedding/setting.py
tock_genai_core/models/embedding/types.py
tock_genai_core/models/embedding/vllm/__init__.py
tock_genai_core/models/embedding/vllm/vllm_em_setting.py
tock_genai_core/models/guardrail/__init__.py
tock_genai_core/models/guardrail/bloomz/__init__.py
tock_genai_core/models/guardrail/bloomz/bloomz_guardrail_setting.py
tock_genai_core/models/guardrail/provider.py
tock_genai_core/models/guardrail/setting.py
tock_genai_core/models/guardrail/types.py
tock_genai_core/models/langfuse/__init__.py
tock_genai_core/models/langfuse/setting.py
tock_genai_core/models/llm/__init__.py
tock_genai_core/models/llm/azure_openai/__init__.py
tock_genai_core/models/llm/azure_openai/azure_openai_llm_setting.py
tock_genai_core/models/llm/provider.py
tock_genai_core-1.5.0.dist-info/METADATA
tock_genai_core-1.5.0.dist-info/WHEEL
tock_genai_core-1.5.0.dist-info/licenses/LICENSE
tock_genai_core-1.5.0.dist-info/RECORD
