Metadata-Version: 2.4
Name: tock-genai-core
Version: 1.5.0
Summary: 
License-File: LICENSE
Author: Baptiste Le Goff
Author-email: baptiste.le-goff@arkea.com
Requires-Python: >=3.9,<4.0
Classifier: Programming Language :: Python :: 3
Classifier: Programming Language :: Python :: 3.9
Classifier: Programming Language :: Python :: 3.10
Classifier: Programming Language :: Python :: 3.11
Classifier: Programming Language :: Python :: 3.12
Classifier: Programming Language :: Python :: 3.13
Classifier: Programming Language :: Python :: 3.14
Requires-Dist: boto3 (>=1.35.96,<2.0.0)
Requires-Dist: google-api-core (>=2.25.1,<3.0.0)
Requires-Dist: google-cloud-secret-manager (>=2.22.0,<3.0.0)
Requires-Dist: google-cloud-storage (>=3.1.0,<4.0.0)
Requires-Dist: kubernetes (>=34.1.0,<35.0.0)
Requires-Dist: langchain (>=0.3.23,<0.4.0)
Requires-Dist: langchain-community (>=0.3.21,<0.4.0)
Requires-Dist: langchain-openai (>=0.3.13,<0.4.0)
Requires-Dist: langchain-postgres (>=0.0.14,<0.0.15)
Requires-Dist: langfuse (>=3.2.1,<4.0.0)
Requires-Dist: opensearch-py (>=2.8.0,<3.0.0)
Requires-Dist: pandas (>=2.2.3,<3.0.0)
Requires-Dist: pydantic-settings (>=2.7.1,<3.0.0)
Requires-Dist: text-generation (>=0.7.0,<0.8.0)
Requires-Dist: tiktoken (>=0.8.0,<0.9.0)
Requires-Dist: uvicorn (>=0.34.0,<0.35.0)
